tiktok_research_client/__init__.py
tiktok_research_client/__main__.py
tiktok_research_client/config.py
tiktok_research_client/data_collection/collect.py
tiktok_research_client/py.typed
tiktok_research_client/utils.py
tiktok_research_client-0.0.21.dist-info/entry_points.txt
tiktok_research_client-0.0.21.dist-info/LICENSE
tiktok_research_client-0.0.21.dist-info/WHEEL
tiktok_research_client-0.0.21.dist-info/METADATA
tiktok_research_client-0.0.21.dist-info/RECORD
