Metadata-Version: 2.1
Name: tiktok-research-client
Version: 0.0.21
Summary: TikTok Research API Client
Home-page: https://github.com/AGMoller/tiktok-research-client
License: MIT
Author: Anders Giovanni Møller
Author-email: andersgiovanni@gmail.com
Requires-Python: >=3.10,<4.0
Classifier: Development Status :: 3 - Alpha
Classifier: License :: OSI Approved :: MIT License
Classifier: Programming Language :: Python :: 3
Classifier: Programming Language :: Python :: 3.10
Classifier: Programming Language :: Python :: 3.11
Requires-Dist: click (>=8.0.1)
Requires-Dist: halo (>=0.0.31,<0.0.32)
Requires-Dist: python-dotenv (>=1.0.0,<2.0.0)
Requires-Dist: requests (>=2.31.0,<3.0.0)
Requires-Dist: tenacity (>=8.2.3,<9.0.0)
Requires-Dist: tornado (==6.3.2)
Requires-Dist: tqdm (>=4.66.1,<5.0.0)
Requires-Dist: types-requests (>=2.31.0.9,<3.0.0.0)
Project-URL: Changelog, https://github.com/AGMoller/tiktok-research-client/releases
Project-URL: Documentation, https://tiktok-research-client.readthedocs.io
Project-URL: Repository, https://github.com/AGMoller/tiktok-research-client
